mcpeasy/__init__.py
mcpeasy/client.py
mcpeasy/types.py
mcpeasy-0.1.0.dist-info/licenses/LICENSE
mcpeasy-0.1.0.dist-info/METADATA
mcpeasy-0.1.0.dist-info/WHEEL
mcpeasy-0.1.0.dist-info/top_level.txt
mcpeasy-0.1.0.dist-info/RECORD
