Metadata-Version: 2.4
Name: mcpeasy
Version: 0.1.0
Summary: The simplest way to use Model Context Protocol in Python
Author-email: Nitish Raj <nitishreact@gmail.com>
License-Expression: MIT
Project-URL: Homepage, https://github.com/jadenitishraj/mcpeasy
Project-URL: Documentation, https://github.com/jadenitishraj/mcpeasy#readme
Project-URL: Repository, https://github.com/jadenitishraj/mcpeasy
Project-URL: Bug Tracker, https://github.com/jadenitishraj/mcpeasy/issues
Keywords: mcp,model-context-protocol,anthropic,llm,ai,client
Classifier: Development Status :: 4 - Beta
Classifier: Intended Audience :: Developers
Classifier: Programming Language :: Python :: 3
Classifier: Programming Language :: Python :: 3.10
Classifier: Programming Language :: Python :: 3.11
Classifier: Programming Language :: Python :: 3.12
Classifier: Topic :: Software Development :: Libraries :: Python Modules
Classifier: Topic :: Scientific/Engineering :: Artificial Intelligence
Requires-Python: >=3.10
License-File: LICENSE
Requires-Dist: mcp>=0.1.0
Provides-Extra: dev
Requires-Dist: pytest>=7.0.0; extra == "dev"
Requires-Dist: pytest-asyncio>=0.21.0; extra == "dev"
Requires-Dist: black>=23.0.0; extra == "dev"
Requires-Dist: ruff>=0.1.0; extra == "dev"
Requires-Dist: mypy>=1.0.0; extra == "dev"
Dynamic: license-file
